[
  {
    "studentName": "Nasim",
    "dateOfBirth": "2026-03-04",
    "aadharNumber": "123456789000",
    "fatherName": "Aboobacker",
    "place": "Paravoor",
    "state": "Karnataka",
    "district": "Kozhikode",
    "pin": "673637",
    "mobileNumber": "0987654321",
    "whatsappNumber": "0987654321",
    "department": "Commerce Academy",
    "photoName": "2995. Sirajul Hasan .JPG",
    "id": "56d11292-3234-48db-9c95-b98f7c953260",
    "createdAt": "2026-03-05T05:46:30.378Z",
    "admissionNumber": "i-831758",
    "status": "Rejected"
  },
  {
    "studentName": "Siraj",
    "dateOfBirth": "2026-03-03",
    "aadharNumber": "123456789009",
    "fatherName": "Aboobacker",
    "place": "Paravoor",
    "state": "Karnataka",
    "district": "Wayanad",
    "pin": "673637",
    "mobileNumber": "1234567899",
    "whatsappNumber": "1234567899",
    "department": "Islamic Heritage",
    "photoName": "00005.00_00_10_30.Still001.jpg.jpeg",
    "id": "5113aff1-eb3f-4e7b-a2dc-3fdb341b5137",
    "createdAt": "2026-03-05T06:10:59.916Z",
    "status": "Pending",
    "admissionNumber": "i-787222"
  },
  {
    "studentName": "Kamal",
    "dateOfBirth": "2026-03-05",
    "aadharNumber": "123456789001",
    "fatherName": "Kamaaa",
    "place": "Paravoor",
    "state": "Karnataka",
    "district": "Wayanad",
    "pin": "673638",
    "mobileNumber": "1234567898",
    "whatsappNumber": "1234567898",
    "department": "Humanities Academy",
    "photoName": "2995. Sirajul Hasan .JPG",
    "id": "055a3071-4a10-4b9e-b7f9-ce6c5e9b5bc7",
    "createdAt": "2026-03-05T06:24:39.918Z",
    "status": "Approved",
    "admissionNumber": "i-820053",
    "photoPath": "/uploads/admissions/i-820053-1772691879919.JPG"
  },
  {
    "studentName": "Ajmal",
    "dateOfBirth": "2026-03-05",
    "aadharNumber": "123456789009",
    "fatherName": "Aboobacker",
    "place": "Paravoor",
    "state": "Tamil Nadu",
    "district": "Kozhikode",
    "pin": "673637",
    "mobileNumber": "9495852500",
    "whatsappNumber": "9495852500",
    "department": "Commerce Academy",
    "photoName": "man-professional-business-casual-young-avatar-icon-illustration_1277826-623.avif",
    "id": "41926c4d-8153-453f-a9b1-fe671bb10f25",
    "createdAt": "2026-03-05T06:47:55.797Z",
    "status": "Pending",
    "admissionNumber": "i-359885",
    "photoPath": "/uploads/admissions/i-359885-1772693275798.avif"
  }
]